{"entities":{"3c2885b1-16b9-46d4-a6a1-2b57e765c0a8":{"name":"Shit","tags":["Pickup","Interact"],"enabled":true,"resource_id":"3c2885b1-16b9-46d4-a6a1-2b57e765c0a8","parent":null,"children":[],"position":[0,0,0],"rotation":[0,0,0],"scale":[0.21779097834412348,0.21779097834412348,0.21779097834412348],"components":{"model":{"enabled":true,"type":"asset","asset":91619498,"materialAsset":null,"castShadows":true,"castShadowsLightmap":true,"receiveShadows":true,"lightmapped":false,"lightmapSizeMultiplier":1,"castShadowsLightMap":true,"lightMapped":false,"lightMapSizeMultiplier":1,"isStatic":false,"layers":[0],"batchGroupId":null},"collision":{"enabled":true,"type":"cone","halfExtents":[0.5,0.5,0.5],"radius":0.18,"axis":1,"height":0.25,"asset":null,"renderAsset":null},"rigidbody":{"enabled":true,"type":"dynamic","mass":1,"linearDamping":0,"angularDamping":0,"linearFactor":[1,1,1],"angularFactor":[1,1,1],"friction":0.5,"restitution":0.1788},"sound":{"enabled":true,"volume":0.3,"pitch":1,"positional":true,"refDistance":1,"maxDistance":20,"rollOffFactor":1,"distanceModel":"linear","slots":{"1":{"name":"Create","loop":false,"autoPlay":false,"overlap":false,"asset":91625603,"startTime":0,"duration":null,"volume":1,"pitch":1}}}}}}}