{"entities":{"f348c3ce-97c1-4ee0-94af-d2665fd235c6":{"name":"Furnace","tags":[],"enabled":true,"resource_id":"f348c3ce-97c1-4ee0-94af-d2665fd235c6","parent":null,"children":["dd8a7317-e08a-4a67-a7a6-de284916eca4","738e333f-c0fc-4744-8690-0fef161aae1e","3522d93d-3b16-4ff8-8b9f-26d823a36e94"],"position":[0,0,0],"rotation":[0,0,0],"scale":[1,1,1],"components":{"sound":{"enabled":true,"volume":0.25,"pitch":1,"positional":true,"refDistance":1,"maxDistance":25,"rollOffFactor":1,"distanceModel":"linear","slots":{"1":{"name":"Damage-1","loop":false,"autoPlay":false,"overlap":false,"asset":88885446,"startTime":0,"duration":null,"volume":1,"pitch":1},"2":{"name":"Damage-2","loop":false,"autoPlay":false,"overlap":false,"asset":88885447,"startTime":0,"duration":null,"volume":1,"pitch":1},"3":{"name":"Destroy","loop":false,"autoPlay":false,"overlap":false,"asset":88885444,"startTime":0,"duration":null,"volume":1,"pitch":1},"4":{"name":"Fire","loop":true,"autoPlay":false,"overlap":false,"asset":89704507,"startTime":0,"duration":null,"volume":1,"pitch":1},"5":{"name":"TurnOff","loop":false,"autoPlay":false,"overlap":false,"asset":89704512,"startTime":0,"duration":null,"volume":1,"pitch":1}}},"script":{"enabled":true,"order":["campfire"],"scripts":{"campfire":{"enabled":true,"attributes":{"fireEntity":"3522d93d-3b16-4ff8-8b9f-26d823a36e94","modelEntity":"dd8a7317-e08a-4a67-a7a6-de284916eca4"}}}}}},"dd8a7317-e08a-4a67-a7a6-de284916eca4":{"name":"Model","tags":[],"enabled":true,"resource_id":"dd8a7317-e08a-4a67-a7a6-de284916eca4","parent":"f348c3ce-97c1-4ee0-94af-d2665fd235c6","children":[],"position":[0,0,0],"rotation":[0,-2.6307689890981034e-38,0],"scale":[0.861,0.861,0.861],"components":{"model":{"enabled":true,"type":"asset","asset":124064203,"materialAsset":null,"castShadows":true,"castShadowsLightmap":false,"receiveShadows":true,"lightmapped":false,"lightmapSizeMultiplier":1,"castShadowsLightMap":true,"lightMapped":false,"lightMapSizeMultiplier":1,"isStatic":false,"layers":[0],"batchGroupId":null}}},"738e333f-c0fc-4744-8690-0fef161aae1e":{"name":"Collision","tags":["Interact","Rock","Land"],"enabled":true,"resource_id":"738e333f-c0fc-4744-8690-0fef161aae1e","parent":"f348c3ce-97c1-4ee0-94af-d2665fd235c6","children":[],"position":[0,1.25,0],"rotation":[0,0,0],"scale":[1,1,1],"components":{"collision":{"enabled":true,"type":"box","halfExtents":[0.672,1.25,0.775],"radius":0.98,"axis":1,"height":1.83,"asset":null,"renderAsset":null,"linearOffset":[0,0,0],"angularOffset":[0,0,0]},"rigidbody":{"enabled":true,"type":"static","mass":1,"linearDamping":0,"angularDamping":0,"linearFactor":[1,1,1],"angularFactor":[1,1,1],"friction":0.5,"restitution":0.5},"script":{"enabled":true,"order":["interactiveCollision"],"scripts":{"interactiveCollision":{"enabled":true,"attributes":{"parentEntity":"f348c3ce-97c1-4ee0-94af-d2665fd235c6","partName":""}}}}}},"3522d93d-3b16-4ff8-8b9f-26d823a36e94":{"name":"Fire","tags":[],"enabled":false,"resource_id":"3522d93d-3b16-4ff8-8b9f-26d823a36e94","parent":"f348c3ce-97c1-4ee0-94af-d2665fd235c6","children":["f8e907bb-aafc-468e-9b8a-0c06e7f8ff67","a248a7df-1cb3-4bb9-bbeb-7e0289aac694"],"position":[0,0.4377773702144623,0.44230649289549673],"rotation":[0,0,0],"scale":[1,1,1],"components":{}},"f8e907bb-aafc-468e-9b8a-0c06e7f8ff67":{"name":"Smoke","tags":[],"enabled":true,"resource_id":"f8e907bb-aafc-468e-9b8a-0c06e7f8ff67","parent":"3522d93d-3b16-4ff8-8b9f-26d823a36e94","children":[],"position":[0.7953110337257385,3.346700996160507,-0.9063204526901245],"rotation":[0,0,0],"scale":[1.9646499766205174,2.2702900875824326,2.2702900875824326],"components":{"sprite":{"enabled":true,"type":"animated","width":1,"height":1,"color":[0,0,0],"opacity":0.779,"flipX":false,"flipY":false,"spriteAsset":null,"frame":0,"speed":1,"batchGroupId":null,"layers":[0],"drawOrder":10,"autoPlayClip":"Fire","clips":{"0":{"name":"Fire","fps":30,"loop":true,"autoPlay":true,"spriteAsset":76934460}}}}},"a248a7df-1cb3-4bb9-bbeb-7e0289aac694":{"name":"Fire","tags":[],"enabled":true,"resource_id":"a248a7df-1cb3-4bb9-bbeb-7e0289aac694","parent":"3522d93d-3b16-4ff8-8b9f-26d823a36e94","children":[],"position":[0,0.43907628998227255,0],"rotation":[0,0,0],"scale":[0.4524610766047001,0.5228503343885662,0.5228503343885662],"components":{"sprite":{"enabled":true,"type":"animated","width":1,"height":1,"color":[1,1,1],"opacity":1,"flipX":false,"flipY":false,"spriteAsset":null,"frame":0,"speed":1,"batchGroupId":null,"layers":[0],"drawOrder":11,"autoPlayClip":"Fire","clips":{"0":{"name":"Fire","fps":40,"loop":true,"autoPlay":true,"spriteAsset":76934458}}}}}}}